[{"id":"46443","boro":"BRONX","astr":"789 ASTOR AVENUE","azip":"10467","lat":"40.8599","lng":"-73.8642","num":"323","officer":"MARK PERLLESHI","org":"KLINA REALTY MGT","delta":"177","a":"51","b":"221","c":"50","i":"1","num2012":"24","num2013":"146","num2014":"323"},{"id":"102592","boro":"BRONX","astr":"735 PELHAM PARKWAY NORTH","azip":"10467","lat":"40.8581","lng":"-73.8661","num":"333","officer":"MARK PERLLESHI","org":"735 PELHAM LLC","delta":"-203","a":"83","b":"208","c":"42","i":"0","num2012":"159","num2013":"536","num2014":"333"}]