[{"id":"20669","boro":"MANHATTAN","astr":"304 EAST 126 STREET","azip":"10035","lat":null,"lng":null,"num":"245","officer":"KEVIN  MURPHY","org":"CITY OF NEW YORK TIL DAMP","delta":"244","a":"79","b":"130","c":"36","i":"0","num2012":"0","num2013":"1","num2014":"245"},{"id":"40514","boro":"MANHATTAN","astr":"30 WEST 132 STREET","azip":"10037","lat":null,"lng":null,"num":"41","officer":"KEVIN  MURPHY","org":"NEW YORK CITY DAMP\/TIL","delta":"41","a":"5","b":"22","c":"14","i":"0","num2012":"0","num2013":"0","num2014":"41"},{"id":"41272","boro":"MANHATTAN","astr":"104 WEST 139 STREET","azip":"10030","lat":null,"lng":null,"num":"59","officer":"KEVIN  MURPHY","org":"CITY OF NY DAMP\/TIL","delta":"52","a":"24","b":"25","c":"10","i":"0","num2012":"5","num2013":"7","num2014":"59"},{"id":"42162","boro":"MANHATTAN","astr":"503 WEST 147 STREET","azip":"10031","lat":null,"lng":null,"num":"44","officer":"KEVIN  MURPHY","org":"CITY OF NEW YORK\/DAMP\/TIL","delta":"44","a":"9","b":"31","c":"4","i":"0","num2012":"0","num2013":"0","num2014":"44"},{"id":"43255","boro":"MANHATTAN","astr":"522 WEST 174 STREET","azip":"10033","lat":null,"lng":null,"num":"161","officer":"KEVIN  MURPHY","org":"CITY OF NY\/DAMP","delta":"128","a":"52","b":"85","c":"24","i":"0","num2012":"25","num2013":"33","num2014":"161"},{"id":"49241","boro":"BRONX","astr":"748 BECK STREET","azip":"10455","lat":null,"lng":null,"num":"200","officer":"KEVIN  MURPHY","org":"CITY OF NEW YORK DPM\/TIL","delta":"189","a":"33","b":"123","c":"44","i":"0","num2012":"8","num2013":"11","num2014":"200"}]