[{"id":"373034","boro":"BROOKLYN","astr":"65 SOUTH PORTLAND AVENUE","azip":"11217","lat":null,"lng":null,"num":"51","officer":"NAZILA  BARDI","org":"65 SOUTH PORTLAND AVENUE","delta":"-29","a":"11","b":"40","c":"0","i":"0","num2012":"60","num2013":"80","num2014":"51"},{"id":"388889","boro":"BROOKLYN","astr":"736 WASHINGTON AVENUE","azip":"11238","lat":null,"lng":null,"num":"203","officer":"NAZILA  BARDI","org":"736 WASHINGTON AVE LLC","delta":"202","a":"25","b":"125","c":"51","i":"2","num2012":"1","num2013":"1","num2014":"203"}]